{"/_app":"pages/_app.js","/about":"pages/about.html","/_error":"pages/_error.js","/add":"pages/add.html","/add-new":"pages/add-new.html","/admin":"pages/admin.html","/api/admin/manage-subscription":"pages/api/admin/manage-subscription.js","/api/admin/users":"pages/api/admin/users.js","/api/auth/chats/[id]":"pages/api/auth/chats/[id].js","/api/auth/change-password":"pages/api/auth/change-password.js","/api/auth/chats":"pages/api/auth/chats.js","/api/auth/login":"pages/api/auth/login.js","/api/auth/confirm":"pages/api/auth/confirm.js","/api/auth/favorites":"pages/api/auth/favorites.js","/api/auth/me":"pages/api/auth/me.js","/api/auth/chats/new":"pages/api/auth/chats/new.js","/api/auth/messages":"pages/api/auth/messages.js","/api/auth/my-offers":"pages/api/auth/my-offers.js","/api/auth/offers/[id]":"pages/api/auth/offers/[id].js","/api/auth/logout":"pages/api/auth/logout.js","/api/auth/register":"pages/api/auth/register.js","/api/auth/offers":"pages/api/auth/offers.js","/api/auth/reset-password":"pages/api/auth/reset-password.js","/api/chat-test":"pages/api/chat-test.js","/api/auth/update-preferences":"pages/api/auth/update-preferences.js","/api/chats":"pages/api/chats.js","/api/chats/[id]":"pages/api/chats/[id].js","/api/chats/[id]/delete":"pages/api/chats/[id]/delete.js","/api/oauth/configure":"pages/api/oauth/configure.js","/api/auth/offerss":"pages/api/auth/offerss.js","/api/notifications/new-offer":"pages/api/notifications/new-offer.js","/api/offers/promote":"pages/api/offers/promote.js","/api/offers/publish-free-promo":"pages/api/offers/publish-free-promo.js","/api/offers":"pages/api/offers.js","/api/offers/[id]":"pages/api/offers/[id].js","/api/ratings/delete/[id]":"pages/api/ratings/delete/[id].js","/api/offers/view":"pages/api/offers/view.js","/api/ratings/add":"pages/api/ratings/add.js","/api/ratings/check":"pages/api/ratings/check.js","/api/offers/save-draft":"pages/api/offers/save-draft.js","/api/ratings/get":"pages/api/ratings/get.js","/api/subscription/cancel":"pages/api/subscription/cancel.js","/api/subscription/auto-renew":"pages/api/subscription/auto-renew.js","/api/subscription/status":"pages/api/subscription/status.js","/api/subscriptions/cancel":"pages/api/subscriptions/cancel.js","/api/subscription/upgrade":"pages/api/subscription/upgrade.js","/api/subscription/create":"pages/api/subscription/create.js","/api/subscriptions/auto-renew":"pages/api/subscriptions/auto-renew.js","/api/subscriptions/upgrade":"pages/api/subscriptions/upgrade.js","/api/subscriptions/create":"pages/api/subscriptions/create.js","/api/subscriptions/purchase":"pages/api/subscriptions/purchase.js","/api/user/offers":"pages/api/user/offers.js","/api/user/stats":"pages/api/user/stats.js","/api/subscriptions/status":"pages/api/subscriptions/status.js","/api/offers/publish-free":"pages/api/offers/publish-free.js","/contact":"pages/contact.html","/debug":"pages/debug.html","/categories":"pages/categories.html","/careers":"pages/careers.html","/help":"pages/help.html","/business":"pages/business.html","/edit/[id]":"pages/edit/[id].html","/login":"pages/login.html","/messages":"pages/messages.html","/offer/[id]":"pages/offer/[id].html","/oauth-setup":"pages/oauth-setup.html","/pricing":"pages/pricing.html","/payment-success":"pages/payment-success.html","/pro":"pages/pro.html","/privacy":"pages/privacy.html","/register":"pages/register.html","/profile":"pages/profile.html","/reset-password":"pages/reset-password.html","/safety":"pages/safety.html","/test-locations":"pages/test-locations.html","/terms":"pages/terms.html","/api/messages/unread-count":"pages/api/messages/unread-count.js","/test-token":"pages/test-token.html","/api/auth/[...nextauth]":"pages/api/auth/[...nextauth].js","/user/[email]":"pages/user/[email].html","/test-promo":"pages/test-promo.html","/api/user/ratings":"pages/api/user/ratings.js","/":"pages/index.html","/api/auth/offers/add":"pages/api/auth/offers/add.js","/api/chats/[id]/upload":"pages/api/chats/[id]/upload.js","/test-oauth":"pages/test-oauth.js","/_document":"pages/_document.js","/404":"pages/404.html"}